pmxbot.nsfw-1.0-py3.5-nspkg.pth
pmxbot/nsfw.py
pmxbot.nsfw-1.0.dist-info/DESCRIPTION.rst
pmxbot.nsfw-1.0.dist-info/METADATA
pmxbot.nsfw-1.0.dist-info/RECORD
pmxbot.nsfw-1.0.dist-info/WHEEL
pmxbot.nsfw-1.0.dist-info/entry_points.txt
pmxbot.nsfw-1.0.dist-info/metadata.json
pmxbot.nsfw-1.0.dist-info/namespace_packages.txt
pmxbot.nsfw-1.0.dist-info/top_level.txt
