Metadata-Version: 2.0
Name: pmxbot.nsfw
Version: 1.0
Summary: NSFW filter for pmxbot
Home-page: https://github.com/yougov/pmxbot.nsfw
Author: YouGov, Plc
Author-email: open-source@yougov.com
License: UNKNOWN
Platform: UNKNOWN
Classifier: Development Status :: 5 - Production/Stable
Classifier: Intended Audience :: Developers
Classifier: License :: OSI Approved :: MIT License
Classifier: Programming Language :: Python :: 3
